README.md
setup.py
algonet/__init__.py
algonet.egg-info/PKG-INFO
algonet.egg-info/SOURCES.txt
algonet.egg-info/dependency_links.txt
algonet.egg-info/requires.txt
algonet.egg-info/top_level.txt