Metadata-Version: 1.0
Name: algonet
Version: 0
Summary: AlgoNet - algorithmic neural networks
Home-page: https://github.com/Felix-Petersen/AlgoNet.git
Author: Felix Petersen
Author-email: mail@felix-petersen.de
License: GPLv3 License
Platform: UNKNOWN
